{
  "type": "minecraft:generic",
  "pools": [
    {
      "rolls": 1,
      "entries": [
        {
          "type": "minecraft:item",
          "name": "minecraft:goat_horn",
          "functions": [
            {
              "function": "minecraft:set_components",
              "components": {
                "minecraft:custom_data": {
                  "warden_pacifier": 1
                },
                "minecraft:item_model": "minecraft:echo_shard",
                "minecraft:item_name": "Warden Flute",
                "minecraft:use_cooldown": {
                  "seconds": 30,
                  "cooldown_group": "warden_pacifier"
                },
                "minecraft:rarity": "epic",
                "minecraft:instrument": "hollow_earth:warden_pacifier"
              }
            }
          ]
        }
      ]
    }
  ]
}