{
  "type": "minecraft:generic",
  "pools": [
    {
      "rolls": 1,
      "entries": [
        {
          "type": "minecraft:item",
          "name": "minecraft:creeper_spawn_egg",
          "functions": [
            {
              "function": "minecraft:set_components",
              "components": {
                "minecraft:entity_data": {
                  "id": "minecraft:creeper",
                  "Tags": [
                    "glob_spawn_creeper"
                  ],
                  "data": {
                    "tag": "glob_spawn_creeper"
                  }
                },
                "minecraft:item_name": {
                  "text": "Glob Spawn Egg",
                  "italic": false
                },
                "minecraft:item_model": "minecraft:nether_wart_block",
                "minecraft:enchantment_glint_override": true
              }
            }
          ]
        }
      ]
    }
  ]
}